{
  "challengeId": "02-todo-list",
  "challengeName": "Todo List Application",
  "difficulty": "intermediate",
  "estimatedTime": "45 minutes",
  "skills": [
    "State Management",
    "Array Manipulation",
    "Event Handling",
    "Controlled Components",
    "Conditional Rendering"
  ],
  "scoring": {
    "functionalTests": 0.40,
    "codeQuality": 0.25,
    "architecture": 0.20,
    "bestPractices": 0.10,
    "aiReview": 0.05
  },
  "filesToCheck": [
    "src/components/TodoList.tsx",
    "src/App.tsx"
  ],
  "patternsRequired": [
    "useState",
    "arrayMethods",
    "controlledComponents",
    "conditionalRendering"
  ]
}
